russtress/__init__.py
russtress/add_dictionary.sm
russtress/constants.py
russtress/model.py
russtress/text_accentAPI.py
russtress/text_model.json
russtress/tokenizer.py
russtress/utils.py
russtress/weights.96.hdf5
russtress-0.1.4.dist-info/METADATA
russtress-0.1.4.dist-info/WHEEL
russtress-0.1.4.dist-info/top_level.txt
russtress-0.1.4.dist-info/RECORD
