Metadata-Version: 2.1
Name: russtress
Version: 0.1.4
Summary: Package that helps you to put lexical stress in russian text
Home-page: https://github.com/MashaPo/russtress
Author: Maria Ponomareva, Kirill Milintsevich
Author-email: ponomarevamawa@gmail.com
License: UNKNOWN
Keywords: nlp russian stress linguistic
Platform: UNKNOWN
Classifier: Development Status :: 4 - Beta
Classifier: Natural Language :: Russian
Classifier: Programming Language :: Python :: 3.5
Classifier: Programming Language :: Python :: 3.6
Classifier: Programming Language :: Python :: 3.7
Classifier: Programming Language :: Python :: 3.8
Classifier: Topic :: Text Processing :: Linguistic
Classifier: Intended Audience :: Education
Requires-Dist: numpy
Requires-Dist: scipy
Requires-Dist: tensorflow
